toolset/__init__.py
toolset/combiner/__init__.py
toolset/combiner/combiner.py
toolset/get_localhost/__init__.py
toolset/get_localhost/get_localhost.py
toolset/get_md5/__init__.py
toolset/get_md5/get_md5.py
toolset/text_encryptor/__init__.py
toolset/text_encryptor/text_encryptor.py
toolset-2019.6.1.dist-info/LICENSE
toolset-2019.6.1.dist-info/METADATA
toolset-2019.6.1.dist-info/WHEEL
toolset-2019.6.1.dist-info/top_level.txt
toolset-2019.6.1.dist-info/RECORD
