Metadata-Version: 2.1
Name: toolset
Version: 2019.6.1
Summary: Tool set.
Home-page: https://github.com/Czw96/ToolSet
Author: Czw
Author-email: 459749926@qq.com
License: UNKNOWN
Platform: UNKNOWN
Classifier: Programming Language :: Python :: 3
Classifier: License :: OSI Approved :: MIT License
Classifier: Operating System :: OS Independent
Requires-Dist: cryptography
